ZMPY3D_TF/ZMPY3D_TF_CLI_BatchShapeScore.py
ZMPY3D_TF/ZMPY3D_TF_CLI_BatchSuperA2B.py
ZMPY3D_TF/ZMPY3D_TF_CLI_BatchZM.py
ZMPY3D_TF/ZMPY3D_TF_CLI_ShapeScore.py
ZMPY3D_TF/ZMPY3D_TF_CLI_SuperA2B.py
ZMPY3D_TF/ZMPY3D_TF_CLI_ZM.py
ZMPY3D_TF/__all__.py
ZMPY3D_TF/__init__.py
ZMPY3D_TF/cache_data/BinomialCache.pkl
ZMPY3D_TF/cache_data/LogG_CLMCache_MaxOrder06.pkl
ZMPY3D_TF/cache_data/LogG_CLMCache_MaxOrder20.pkl
ZMPY3D_TF/lib/__init__.py
ZMPY3D_TF/lib/calculate_ab_rotation_02_all_tf.py
ZMPY3D_TF/lib/calculate_ab_rotation_02_tf.py
ZMPY3D_TF/lib/calculate_bbox_moment_07_tf.py
ZMPY3D_TF/lib/calculate_bbox_moment_2_zm05_tf.py
ZMPY3D_TF/lib/calculate_box_by_grid_width.py
ZMPY3D_TF/lib/calculate_molecular_radius_04_tf.py
ZMPY3D_TF/lib/calculate_zm_by_ab_rotation01_tf.py
ZMPY3D_TF/lib/eigen_root_tf.py
ZMPY3D_TF/lib/eigen_root_tf2.py
ZMPY3D_TF/lib/fill_voxel_by_weight_density04.py
ZMPY3D_TF/lib/get_3dzd_121_descriptor_02_tf.py
ZMPY3D_TF/lib/get_bbox_moment_xyz_sample_01_tf.py
ZMPY3D_TF/lib/get_ca_distance_info_tf.py
ZMPY3D_TF/lib/get_descriptor_property.py
ZMPY3D_TF/lib/get_global_parameter02.py
ZMPY3D_TF/lib/get_mean_invariant_03_tf.py
ZMPY3D_TF/lib/get_pdb_xyz_ca02.py
ZMPY3D_TF/lib/get_residue_gaussian_density_cache02.py
ZMPY3D_TF/lib/get_residue_radius_map01.py
ZMPY3D_TF/lib/get_residue_weight_map01.py
ZMPY3D_TF/lib/get_total_residue_weight.py
ZMPY3D_TF/lib/get_transform_matrix_from_ab_list02_tf.py
ZMPY3D_TF/lib/pdb_2_voxel_dataset02.py
ZMPY3D_TF/lib/pdb_2_voxel_xyz_weight_dataset.py
ZMPY3D_TF/lib/read_file_as_string_list.py
ZMPY3D_TF/lib/set_pdb_xyz_rot_m_01.py
ZMPY3D_TF/lib/write_string_list_as_file.py
ZMPY3D_TF-0.0.2.dist-info/LICENSE
ZMPY3D_TF-0.0.2.dist-info/METADATA
ZMPY3D_TF-0.0.2.dist-info/WHEEL
ZMPY3D_TF-0.0.2.dist-info/entry_points.txt
ZMPY3D_TF-0.0.2.dist-info/top_level.txt
ZMPY3D_TF-0.0.2.dist-info/RECORD
